setup.py
src/tajo/__init__.py
src/tajo/channel.py
src/tajo/client.py
src/tajo/connection.py
src/tajo/datatypes.py
src/tajo/fetchresultset.py
src/tajo/memoryresultset.py
src/tajo/queryid.py
src/tajo/querystate.py
src/tajo/resultset.py
src/tajo/rowdecoder.py
src/tajo/proto/CatalogProtos_pb2.py
src/tajo/proto/ClientProtos_pb2.py
src/tajo/proto/ContainerProtocol_pb2.py
src/tajo/proto/DataTypes_pb2.py
src/tajo/proto/InternalTypes_pb2.py
src/tajo/proto/Plan_pb2.py
src/tajo/proto/PrimitiveProtos_pb2.py
src/tajo/proto/QueryCoordinatorProtocol_pb2.py
src/tajo/proto/QueryMasterClientProtocol_pb2.py
src/tajo/proto/QueryMasterProtocol_pb2.py
src/tajo/proto/ResourceTrackerProtocol_pb2.py
src/tajo/proto/RpcProtos_pb2.py
src/tajo/proto/Security_pb2.py
src/tajo/proto/TajoIdProtos_pb2.py
src/tajo/proto/TajoMasterClientProtocol_pb2.py
src/tajo/proto/TajoWorkerProtocol_pb2.py
src/tajo/proto/TestProtos_pb2.py
src/tajo/proto/__init__.py
src/tajo/proto/tajo_protos_pb2.py
src/tajo/proto/yarn_protos_pb2.py
src/tajo/rpc/__init__.py
src/tajo/rpc/channel.py
src/tajo/rpc/controller.py
src/tajo/rpc/proto_util.py
src/tajo/rpc/service.py
src/tajo_client.egg-info/PKG-INFO
src/tajo_client.egg-info/SOURCES.txt
src/tajo_client.egg-info/dependency_links.txt
src/tajo_client.egg-info/requires.txt
src/tajo_client.egg-info/top_level.txt