Metadata-Version: 1.1
Name: tajo-client
Version: 0.0.4
Summary: a Python implementation of Tajo Client
Home-page: http://github.com/charsyam/python-tajo-client/
Author: DaeMyung Kang
Author-email: charsyam@gmail.com
License: UNKNOWN
Platform: UNKNOWN
Classifier: Intended Audience :: Developers
Classifier: License :: OSI Approved :: Apache Software License
Classifier: Operating System :: OS Independent
Classifier: Programming Language :: Python
Classifier: Topic :: Software Development :: Libraries :: Python Modules
